{
  "featuredTitle": "Let’s keep going",
  "featuredDescription": "Continue where you left off last time",
  "enrolledModulesTitle": "Your learning programs",
  "enrolledModulesSubtitle": "",
  "noModuleTitle": "Want to start your learning experience?",
  "noModuleExplore": "Explore",
  "enrolledOffersTitle": "Language offers",
  "noCoutryDescription": "Please select your country of residence so we can prepare your environment.",
  "noCountrySet": "Set your country",
  "updatesMainTitle": "Update",
  "updatesTitle": "{{orgDisplayName}} Campus is now available in Arabic and Turkish.",
  "updatesText": "Change your language preference on the Profile Page to check it out.",
  "countrySpecificTitle": "More on Campus",
  "mentoringTitle": "Mentoring",
  "mentoringDesciption": "3 months online course with mentor",
  "referralShareText": "Join me at {{orgDisplayName}}",
  "referralCardTitle": "Share {{orgDisplayName}} with your friends",
  "referralCopy": "Copy",
  "referralCopied": "Copied",
  "applicationCheckTitle": "Application checklist",
  "applicationCheckText": "Prepare your university application",
  "moduleFeaturedBtn": "Continue learning",
  "streakWeeks": {
    "congratulation": "Congratulations!",
    "achievement": "You were active for",
    "firstAchievementWeek": "Start your new streak now!",
    "homepageAchievement": "week",
    "homepageAchievement_plural": "weeks in a row",
    "achievementWeeks": "week",
    "achievementWeeks_plural": "weeks in a row",
    "buttonCta": "Keep on rocking!",
    "headline": "Your activity",
    "subtitle": "Learn every week to collect achievements",
    "shareText": "I have learned ",
    "shareTextEnd": " weeks in a row on {{orgDisplayName}}! ",
    "sharetextFull": "I have learned {{1}} weeks in a row on {{orgDisplayName}}!"
  },
  "mapSearch": "Search city",
  "mapListHeadline": "Students in {{city}}",
  "mapHeadline": "Meet students around you",
  "mapSubTitle": "Study together with nearby students",
  "studentCount": "{{0}} student",
  "studentCount_plural": "{{0}} students",
  "mapNoResultsInfo": "No students in this city yet",
  "mapBackBtn": "Back to {{city}}",
  "contactBtn": "Message {{name}}",
  "since": "Since",
  "loadMore": "Load more",
  "memberSince": "Member since {{year}}"
}