{
    "register": {
        "pleaseWait": "Espere, por favor...",
        "registerHeadline": "Registro",
        "initial": {
            "emailButton": "Registrarse con email",
            "termsText": "Al continuar acepta nuestros",
            "termsLink": "Política de Privacidad/Términos de utilización",
            "alreadyUserTitle": "¿Ya es usuario?",
            "alreadyUserLink": "Entrar",
            "or": "o"
        },
        "registerWithEmail": {
            "labelEmail": "Email",
            "labelPassword": "Su contraseña",
            "buttonRegister": "Registrarse",
            "alreadyUserTitle": "¿Ya es usuario?",
            "alreadyUserLink": "Entrar",
            "errorEmail": "Debe ser una dirección de email válida y no puede contener espacios",
            "errorKironEmail": "Por favor utilice 'Continuar con Google' para entrar",
            "errorEmailTaken": "Esta dirección de email ya está en uso",
            "errorShortPassword": "Su contraseña debe tener al menos 8 caracteres",
            "errorLowercase": "La contraseña debe contener como mínimo una letra minúscula",
            "errorUppercase": "La contraseña debe contener como mínimo una letra mayúscula",
            "errorNumber": "La contraseña debe contener como mínimo un número",
            "errorSpecialCharacter": "La contraseña debe contener como mínimo un carácter especial excepto < o >",
            "emailSentTitle": "¡Casi ha terminado!",
            "emailSentDescription01": "Mire su email.",
            "emailSentDescription02": "Le hemos enviado un email para activar su cuenta.",
            "termsText": "Al continuar acepta nuestros",
            "termsLink": "Política de Privacidad/Términos de utilización"
        },
        "registerConfirmed": {
            "title": "¡Casi ha terminado!",
            "description": "Estamos preparando su cuenta...",
            "acceptTerms": "Aceptar términos y condiciones de uso"
        }
    },
    "explore": {
        "categories": "Categorías",
        "search": "Buscar",
        "searchInitial": "Buscar algo",
        "searchInitialSubOne": "",
        "searchInitialSubTwo": "",
        "searchInitialSubThree": "",
        "searchInitialSubFour": "",
        "searchInitialSubFive": "",
        "searchInitialSubSix": "",
        "noResults": "No se han encontrado resultados para",
        "skillBoosterPrograms": "Skill Booster Programs",
        "course": "Curso",
        "courses": "Cursos",
        "recommended": "Recomendado por",
        "showAll": "Mostrar todo",
        "collapse": "Colapsar",
        "programs": "Programas",
        "heading": "Explora nuestros programas"
    },
    "success": {
        "introTitle": "¡Su historia de éxito!",
        "introDescription": "¡Vuelva cada día y finalice cursos para más!",
        "titleNew": "Tus últimos logros",
        "courseVer": "✓ ¡Verificado!",
        "courseVerificationPend": "Esperando verificación",
        "verifyCta": "VERIFICAR",
        "autoVerified": "Auto-verificado",
        "imgAlt": "Su historia de éxito",
        "visit": "visitar",
        "daysVisited": "días visitado",
        "courseComplete": "curso completado",
        "coursesComplete": "cursos completados",
        "first": "1º",
        "shortProgram": "Programa corto",
        "completed": "completado",
        "finishedCourses": "Cursos completados",
        "toBeVerified": "por verificar",
        "coursesFinished": "curso terminado",
        "coursesFinished_plural": "coursos terminados",
        "coursesLeft": "cursos restantes",
        "coursesLeft_plural": "cursos restantes",
        "language": {
            "en": "Inglés",
            "de": "Alemán",
            "progressPopup": "Muchas universidades requieren un certificado oficial de idioma nivel C1 de uno de los siguientes institutos: Goethe, DSH, TestDAF y TELC. Le daremos soporte durante el proceso.",
            "currentLevel": "Nivel Actual",
            "languageProgress": "progreso en el idioma",
            "btnDesc": "¿Ha terminado un curso?",
            "btnLabel": "Añada un Certificado",
            "btnLabelCertificate": "Certificados",
            "confirmDelete": "¿Está seguro de que lo quiere borrar?",
            "save": "Guardar",
            "cancel": "Cancelar",
            "addCourse": "Añadir un certificado",
            "other": "Otro",
            "level": "Nivel",
            "courseName": "Nombre del curso",
            "titleOfCeritificate": "Título de su certificado",
            "certificateDate": "Fecha del certificado",
            "certificateDateDesc": "Añadir un certificado le ayudará con su solicitud de ingreso en la universidad.",
            "yes": "Sí",
            "no": "No"
        },
        "addedToWallet": "Añadido a tu cartera",
        "addToWallet": "Añadir a tu cartera"
    },
    "transcriptOfRecords": {
        "descriptionSupport": "¡Estupendo, ya tiene muchos cursos verificados! Si está solicitando ingreso en una universidad, puede pedir un PDF con una lista de sus logros. Por favor contacte el soporte de {{orgDisplayName}}"
    },
    "fileUpload": {
        "description": "Clique aquí o arrastre y suelte ficheros para subir su certificado.<br />(También puede subir su certificado más tarde)",
        "exampleDesc": "Por favor clique en la imagen para ver un ejemplo de certificado en una pestaña nueva",
        "verificationExample": "Ejemplo de verificación",
        "save": "Guardar",
        "cancelUploadConfirmation": "¿Seguro que quiere cancelar la subida del archivo?",
        "cancelUpload": "Cancelar",
        "maxFilesLimitReached": "No se puede subir más de un archivo simultáneamente",
        "removeFile": "Eliminar",
        "fileTypeNotSupported": "Lo sentimos, este tipo de archivo no está permitido"
    },
    "moduleStatus": {
        "hour": "hora",
        "hours": "horas",
        "certificate": "Certificado",
        "credits": "créditos",
        "finished": "¡Terminado!"
    },
    "algoliaResults": {
        "certificate": "Certificado",
        "credits": "créditos"
    },
    "dateInput": {
        "day": "Día:",
        "month": "Mes:",
        "year": "Año:",
        "ago": "Hace {{elapsedTime}} días"
    },
    "shortProgram": {
        "loading": "Cargando Programa",
        "studyTrack": "Study Track Module",
        "skillBooster": "Skill Booster Program",
        "notFoundTitle": "Programa desconocido",
        "notFoundDesc": "Este programa no existe o no pertenece a su itinerario de aprendizaje. Por favor vuelva al listado para ver todos los programas disponibles para usted.",
        "certificateDownload": "Descargar Certificado",
        "certificatePreview": "Esto es una vista previa de <1/><2>{{2}}</2>",
        "certificateStart": "Empiece hoy este programa para acceder a todas las unidades",
        "btnStart": "Empezar este programa",
        "certificateModule": "Esto es un módulo en su programa de estudios",
        "certificateCredit": "Créditos:",
        "certificateImgAlt": "Certificado de {{orgDisplayName}}",
        "certficateBtnUnenroll": "Desinscribirse",
        "certficateBtnContinue": "Continuar estudiando",
        "certificateBtnStart": "Empezar a estudiar",
        "certificateFinishText": "¡Estupendo! <1/>Termine todas las unidades para obtener un certificado.",
        "noCertificateFinishText": "¡Bien hecho! <1/>¡Siga con este ritmo!",
        "certificateProgress": "Progreso:",
        "certificateCounter": "Ha terminado {{0}} de {{1}} unidades",
        "removeYes": "Sí",
        "removeNo": "No",
        "removeTitle": "Desinscribirse del curso",
        "removeQuestion": "¿Está seguro de que desea desinscribirse de este curso?",
        "addModuleSuccess": "Éxito",
        "addModuleBtnContinue": "Continuar mirando",
        "addModuleBtnStart": "Comenzar ahora la primera unidad",
        "addModuleText": "Este skill booster program ha sido añadido a su pestaña de inicio",
        "enrollModuleBtnNo": "Ahora no",
        "enrollModuleBtnStart": "Comenzar a estudiar",
        "enrollModuleText": "Hola {{0}}, esto es parte de su programa de estudios <1>{{- 1}}</1>. ¿Quiere empezarlo para aprender <3>{{- 3}}</3>?",
        "showContent": "Mostrar contenido extra",
        "hideContent": "Esconder contenido extra",
        "titleModule": "Módulo",
        "titleSkillBooster": "Skill Booster Program",
        "titleUnits": "unidades",
        "titleDesc": "Descripción",
        "downloadTranscriptBtn": "Descargar expediente",
        "unitComplete": "¡Unidad <1/> completada!",
        "rateHelp": "Ayude a otros estudiantes puntuando este curso",
        "notNow": "Ahora no",
        "rate": "Puntuar",
        "thankYou": "Gracias",
        "addComment": "Añadir un comentario",
        "send": "Enviar",
        "thanksTitle": "¡Estupendo trabajo!",
        "thanksSubtitle": "Estamos orgullosos de usted",
        "thanksShare": "¡Compártalo con sus amigos!",
        "nextUnitTitle": "Siguiente...",
        "nextUnitSkipTitle": "Terminar esta unidad",
        "nextUnitContinue": "Continuar aprendiendo",
        "nextUnitCta": "¿Qué puedo aprender ahora?",
        "nextUnitCertificate": "Ha conseguido un certificado",
        "nextUnitDownload": "Descargar ahora",
        "feedbackLike": "¿Qué es lo que más le gustó?",
        "feedbackDislike": "¿Qué es lo que no le gustó?",
        "feedbackNext": "Siguiente",
        "feedbackLoading": "Cargando lección",
        "enrollCourseLimitText": "Sorry, you can enroll in up to {{0}} courses",
        "type": "Programa",
        "selfPaced": "Autodidacta",
        "addProgramText": "Hemos añadido este programa a su página de inicio",
        "titleProgram": "Programa",
        "Text": "Lo sentimos, solamente se puede inscribir a {{0}} cursos",
        "stayInOldProgram": "Quiero quedarme en la versión antigua del programa",
        "updatedProgramMaintained": "No te preocupes, tu progreso se guardará aunque te registres en la nueva versión del programa.",
        "updatedProgramText": "¡Hemos actualizado el programa en el que te registraste! Te recomendamos unirte a la nueva versión del programa haciendo clic en",
        "updatedProgram": "¡El programa se ha actualizado!",
        "evaluate": "Evalúa este curso",
        "evaluateHelp": "Ayúdanos a mejorar evaluando este curso",
        "helpReviewCourse": "Ayuda a otros estudiantes valorando este curso.",
        "btnShareReview": "Comparte tu opinión",
        "shareYourOpinion": "Comparte tu opinión con otros estudiantes",
        "continueNextCourseBtn": "Continúa con el siguiente curso",
        "backToProgramBtn": "Vuelve al programa",
        "subHeaderNextUp": "Lo siguiente en este programa",
        "thankYouHeader": "¡Gracias por tu valoración!",
        "shareYourProgress": "Comparte el avance con tus amigos",
        "completedAProgramHeader": "¡Hurra! Has completado este programa.",
        "earnedACertificateHeader": "¡Hurra! Te has ganado un certificado.",
        "downloadCertificateBtn": "Descarga el certificado",
        "sentCertificateDatawalletBtn": "Envía el certificado a tu cartera de datos",
        "socialShareTextBtn": "He completado {{courseDenomination}}",
        "exploreMoreProgramsBtn": "Descubre más programas",
        "completedACourseHeader": "¡Hurra! Has completado este curso."
    },
    "shortProgramUnitLesson": {
        "lessonNavigatorCtaNext": "Siguiente"
    },
    "unitCard": {
        "liveUnit": "Unidad en vivo",
        "kironUnit": "Unidad de {{orgDisplayName}}",
        "externalUnit": "Unidad externa",
        "started": "¡Comenzada!",
        "completed": "¡Completada!",
        "live": "EN VIVO",
        "provided": "Proporcionada por",
        "courseProvider": "Proporcionada por <1>{{1}}</1>",
        "hoursAbbreviation": "h",
        "weeksAbbreviation": "w",
        "multiplier": "x",
        "type": "Curso",
        "selfPaced": "Autodidacta",
        "inProgress": "En curso",
        "courseType": {
            "event": "{{0}} Evento",
            "event_plural": "{{0}} Eventos",
            "project": "{{0}} Proyecto",
            "project_plural": "{{0}} Proyectos",
            "course": "{{0}} Curso",
            "course_plural": "{{0}} Cursos"
        },
        "unit": "{{0}} Unidad",
        "unit_plural": "{{0}} Unidades"
    },
    "courseraProgress": {
        "title": "Progreso en Coursera",
        "subtitle": "¿Por qué no se actualiza mi progreso en Coursera en {{orgDisplayName}} Campus?",
        "body": "Puede tomar 2-3 días antes de que su progreso en Coursera aparezca en {{orgDisplayName}} Campus. Esto no significa que su progreso no se actualice. ¡Por favor vuelva pronto para ver su progreso actualizado!"
    },
    "pendingApplicationStatus": {
        "accountStatus": "Account status: <1>Pending approval</1>",
        "pendingExplanation": "The screening process usually takes around 2 weeks.",
        "infoMessage": "You need approval to enroll in this program"
    },
    "unitPage": {
        "register": "Registrarse",
        "completionInfo": "Tu instructor marcará este curso como completado después de revisarlo",
        "unenroll": "Desinscribirse",
        "unenrollLoading": "actualizando...",
        "reviewCount": "{{0}} valoración",
        "reviewCount_plural": "{{0}} valoraciones",
        "noReviews": "No hay valoraciones todavía",
        "preventEnroll": "Esta unidad únicamente está disponible después de que tus documentos hayan sido cargados y verificados",
        "updating": "actualizando…",
        "participantsCount": "{{0}} estudiante en la unidad",
        "participantsCount_plural": "{{0}} estudiantes en la unidad",
        "course": "Curso",
        "unit": "Unidad",
        "notificationPopupTitle": "Construye un hábito de aprendizaje",
        "notificationPopupDescription": "Habilita las notificaciones para obtener recordatorios sobre tus cursos.",
        "notificationPopupMaybeLater": "Quizás más tarde",
        "notificationPopupCoolThanks": "¡Genial, gracias!",
        "hostedCourse": {
            "start": "Comenzar la Unidad",
            "finish": "Completar la Unidad",
            "retake": "Retomar Unidad"
        },
        "regularMooc": {
            "finished": "Marcar como Terminado",
            "start": "Comenzar en",
            "notFinished": "Haz click aquí si aun no has terminado"
        },
        "continue": "Continuar",
        "confirm": "Confirmar",
        "cancel": "Cancelar",
        "continueIn": "Continuar en {{0}}",
        "openIn": "Abrir Curso en {{0}}",
        "learningOutcomesTitle": "Aprenderás a ...",
        "contentTitle": "Contenido en esta Unidad",
        "minutes": "{{0}} minuto",
        "minutes_plural": "{{0}} minutos",
        "messageBoard": {
            "description": "Comunícate con otros estudiantes, preséntate, y conoce a otros estudiantes aquí.",
            "reportMessage": "Si encuentra un mensaje ofensivo, violento o de publicidad ajena a esta plataforma, por favor mande un correo electrónico a <1>student-support@kiron.ngo</1>. ",
            "messageButton": "Mensaje",
            "defaultText": "Todavía no se ha iniciado una conversación. Saluda a los otros participantes de este proyecto.",
            "confirmDeleteReply": "¿Está seguro/a que quiere borrar su respuesta?",
            "confirmDeleteMessage": "¿Está seguro/a que quiere borrar su mensaje? Recuerde que todas las respuestas serán también eliminadas.",
            "cancel": "Cancelar",
            "delete": "Borrar",
            "reply": "Responder",
            "chatHeading": "Chat",
            "loading": "Enviando",
            "inputFieldPlaceholder": "Mensaje",
            "sendButton": "Enviar"
        },
        "verification": {
            "failed": "La Verificación falló - Intenta de nuevo",
            "pending": "Verificación pendiente",
            "uploadPrompt": "Carga tu certificado",
            "popupTitle": "Carga tu Certificado",
            "popupDescription": "Da click en la imagen para ver un ejemplo de un certificado en una nueva pestaña"
        },
        "live": {
            "nextSession": "Próxima sesión en vivo",
            "joinSession": "Unirse a sesión",
            "allSessionsCompleted": "Todas tus sesiones en vivo están completadas.",
            "markFinished": "Marcar como completado",
            "registerBefore": "Regístrate antes de ",
            "startDate": "Fecha de inicio",
            "endDate": "Fecha final",
            "pressMarkFinished": "Presiona \"Marcar como completado\" para completar esta Unidad.",
            "unregister": "Desregístrate",
            "registered": "Registrado",
            "participantsCount": "Tu y {{0}} otra persona",
            "participantsCount_plural": "Tu y {{0}} otras personas",
            "isExpired": "El registro ya no es posible. Nuevas fechas de inicio serán publicadas pronto.",
            "noSessions": "No hay próximas sesiones en vivo para esta unidad. Por favor checa de nuevo más tarde.",
            "selectSession": "Selecciona una sesión para continuar",
            "signUp": "Regístrate",
            "showTimes": "Mostrar horarios",
            "localTimeZone": "Todos los horarios son mostrados en tu hora local",
            "openUntil": "Abierto hasta {{0}}",
            "closed": "Cerrado",
            "to": "hasta",
            "attendConfirmationTitle": "Puedes atender?",
            "attendConfirmationDescription01": "Al registrarte en esta unidad en vivo, te estás compometiendo a atender a todas las citas en tus sesiones seleccionadas.",
            "attendConfirmationDescription02": " Las plazas son limitadas. Si no puedes asistir, por favor, no te registres. Así otros estudiantes podrán participar.",
            "cancelConfirmationTitle": "¿Estás seguro/a?",
            "cancelConfirmationDescription01": "Si continuas, te borrarás de la lista de participantes de esta unidad y no podrás unirte a la próxima sesión",
            "cancelConfirmationDescription02": "Si las sesiones ya han empezado, no podrás registrarte hasta el próximo evento",
            "liveSessionLinkReminder": "El enlace de acceso a tu clase en línea se activará el mismo día de la sesión.",
            "appointmentFrequency": "Se repite cada semana hasta {{0}}",
            "appointmentFrequency_plural": "Se repite cada {{1}} semanas hasta {{0}}"
        },
        "retakeCourse": "Repetir el curso",
        "startLearning": "Empezar a estudiar",
        "howItWorks": "¿Cómo funciona?",
        "sureLeave": "¿Seguro que quieres salir del curso?",
        "noStay": "No, quiero continuar",
        "yesLeave": "Sí, salir del curso"
    },
    "landingPage": {
        "login": "Acceder",
        "search": "Explora nuestros cursos",
        "startLearning": "Empiece a estudiar"
    },
    "lessonTest": {
        "takeTest": "Empezar el test",
        "passHint": "Por favor, apruebe el test para continuar",
        "answerHint": "Responda un mínimo de {{0}} para aprobar el test.",
        "question": "preguntas",
        "questions": "Pregunta",
        "send": "Enviar",
        "thankParticipation": "TGracias por participar",
        "congrats": "¡Enhorabuena, ha completado la unidad! Puede repetir el test o seguir adelante.",
        "testAgain": "Parece que todavía no está listo para continuar. Por favor, revise el contenido y repita el test para continuar.",
        "testNonRetakeable": "Lo sentimos, no has conseguido puntos suficientes para aprobar el test. Puedes seguir aprendiendo en esta unidad pero no podrás marcarla como completada.",
        "retakeTest": "Repetir el test",
        "sending": "Enviando resultados...",
        "continueHint": "Por favor, comente en “{{0}}“ para poder continuar"
    },
    "attachmentItem": {
        "download": "Descargar",
        "delete": "Borrar",
        "deleting": "Borrando archivo...",
        "uploading": "Cargando archivo...",
        "uploadingPleaseWait": "Por favor espera"
    },
    "certificate": {
        "noFirstAndLastNameProvided": "Por favor, escriba su nombre y apellidos para poder obtener su certificado.",
        "contactSupport": "Pedir ayuda"
    },
    "appointmentCardInfo": {
        "repeats": "Se repite cada",
        "week": "semana",
        "weeks": "semanas"
    },
    "questionnaire": {
        "contactUs": "Recuerde que siempre puede volver atrás y contactar con nosotros si tiene alguna pregunta. ¡Ahora empecemos a aprender sobre {{0}} en Alemania!",
        "innerText": "{{0}}",
        "submitQuestionnaireText": "Por favor, siga las instrucciones para rellenar los campos vacíos y guarde sus respuestas haciendo clic en \"Enviar\".",
        "submitQuestionnaire": "Enviar cuestionario",
        "fillInText": "Para averiguar en qué punto está usted en este proceso y cuál es el siguiente paso, por favor responda a las preguntas. Esta información nos ayudará a darle mejor apoyo y orientación.",
        "fillIn": "Rellenar cuestionario",
        "cardInfoText": "Encontrará información en la parte superior de cada categoría. Asegúrese que ve el video y lee el texto al inicio para saber todo lo que necesitará para ir a la universidad.",
        "cardInfo": "Información de la tarjeta",
        "goBackText": "Para volver atrás y ver la lista completa, haga clic aquí.",
        "goBack": "Volver atrás",
        "firstCategoryText": "Ahora está en la primera categoría sobre <1>{{1}}</1>",
        "firstCategory": "Primera categoría",
        "errorLoading": "Ha habido en error cargando los {{0}} certificados de idiomas",
        "seeOtherStudents": "Ver más información sobre otros estudiantes de Kiron…",
        "updatedInfo": "¡Hola! En esta página puede leer la información más reciente sobre Kiron, nuestros cursos, consejos para el estudio y algunos artículos interesantes que seleccionamos para usted. Haga click en los títulos para ver al texto entero y ¡vuelva a esta página cuando quiera para ver las novedades!",
        "newsFeed": "Noticias",
        "feedBack": "Compartir mi opinión",
        "isItUsefull": "Si cree que es útil, por favor comparta su opinión. ¡Solamente tardará un minuto!",
        "opinion": "¿Qué opina sobre esta nueva página?",
        "reset": "¿Está seguro/a de que quiere repetir el cuestionario?",
        "retake": "Repetir el cuestionario",
        "prevPage": "Página anterior",
        "nextPage": "Página siguiente",
        "submitResult": "Por favor haga clic en \"Enviar\" para ver su resultado.",
        "submit": "Enviar",
        "findUniversity": "Indique su calificación de acceso a la universidad en la categoría \"Educación Previa\" y vuelva aquí",
        "loadingLangCertificate": "Cargando certificados de idiomas"
    },
    "downloadRecording": "Descargar la grabación",
    "downloadRecordings": "Descargar todas las grabaciones de la lección",
    "downloadAllLessonsRecordings": "Descargue todas las grabaciones de las unidades de este curso",
    "downloadLessonRecordings": "Descargue todas las grabaciones",
    "course": {
        "details": "Detalles",
        "registerBefore": "Regístrate antes de",
        "verifyAccount": "Por favor verifique su cuenta para obtener acceso ilimitado a cursos y certificados gratuitos",
        "save": "Guardar",
        "youWillGetNotified": "Recibirás una notificación cuando hayamos terminado",
        "close": "Cerrar",
        "documentsInReview": "Sus documentos están siendo verificados.",
        "students": "Estudiantes",
        "contains": "Contiene",
        "freeCertificate": "Certificado gratuito para estudiantes de Kiron.",
        "howItWorks": "Mira cómo funciona.",
        "itOnlyTakes": "Solamente tomará 5 minutos",
        "lessonCount": "lección",
        "lessonCount_plural": "lecciones",
        "averageRating": "Valoración media de otros estudiantes:",
        "editRating": "Edita tu valoración",
        "rating": "{{0}} valoración",
        "rating_plural": "{{0}} valoraciones",
        "hour": "{{0}} hora",
        "hour_plural": "{{0}} horas",
        "projectChatText": "Podrás hablar con otros participantes cuando te hayas inscrito a este proyecto.",
        "courseChatText": "Podrás hablar en el chat cuando te hayas registrado en este curso.",
        "reviewsTab": "Valoraciones",
        "overviewTab": "Descripción",
        "chatTab": "Chat",
        "appointmentsTab": "Citas",
        "aboutTab": "Acerca de",
        "noLessons": "Estamos trabajando en las nuevas lecciones y las publicaremos muy pronto.",
        "lesson": "Lección",
        "about": "Acerca de",
        "lessonsTitle": "Lecciones",
        "wellDone": "¡Buen trabajo! Has completado este curso.",
        "congratulations": "¡Enhorabuena!",
        "verify": "Verifica tu cuenta para empezar a estudiar este curso.",
        "deadline": "Fecha límite de inscripción",
        "duration": "Duración",
        "offeredBy": "Ofrecido por",
        "reviews": "Valoraciones",
        "participants": "Participantes",
        "finishLessons": "Finaliza todas las lecciones para completar este curso.",
        "onYourWay": "¡Vas por buen camino!",
        "estimate": "Tiempo estimado de estudio",
        "attachmentsTab": "Archivos adjuntos",
        "isLocked": "This course is locked",
        "lockedMessage": "You are required to complete <1>Unit: {{0}}</1> to unlock this course",
        "badges": "Insignias"
    },
    "errors": {
        "lostPageDesc": "No podemos encontrar lo que buscas.",
        "lostPage": "Esta página se ha perdido",
        "lostLessonDesc": "No podemos encontrar la lección que estás buscando.",
        "lostLesson": "Esta lección se ha perdido",
        "lostProgramDesc": "No podemos encontrar el programa que estás buscando.",
        "lostProgram": "Este programa se ha perdido",
        "backToCourse": "Volver al curso",
        "goToExplore": "Ir a Explorar",
        "backToProgram": "Volver al programa",
        "lostCourseDesc": "No podemos encontrar el curso que estás buscando.",
        "lostCourse": "Este curso se ha perdido",
        "lostCategoryDesc": "No podemos encontrar la categoría que estás buscando.",
        "lostCategory": "Esta categoría se ha perdido",
        "tryAgain": "Intentarlo otra vez",
        "internetBrokenDesc": "Lo sentimos, no podemos cargar tus datos en este momento.",
        "internetBroken": "El Internet no funciona",
        "completeCourses": "Debes completar todos los cursos para descargar tu certificado.",
        "almostThere": "Ya casi has llegado",
        "backHome": "Volver al inicio",
        "techProblemDesc": "Lo sentimos, esta página no funciona correctamente.",
        "techProblem": "Hemos detectado un problema técnico",
        "expiredLink": "El enlace ha caducado",
        "expiredLinkDesc": "Lo sentimos, esta página ya no se encuentra disponible."
    },
    "stayTuned": "¡Pronto te daremos más información.",
    "participation": {
        "isUserTutor": "Usted ha sido asignado/a como tutor/a de este proyecto"
    },
    "category": "Categoría",
    "moreBtn": "Ver más",
    "lessBtn": "Minimizar",
    "survey": {
        "takeSurveyTitle": "Rellena tu cuestionario de autoevaluación",
        "recommendedContentSubtitle": "Te recomendaremos contenido en base a los resultados. Puedes rellenar el test más adelante desde tu perfil.",
        "recommendedContentSubtitleProfilePage": "Te recomendaremos contenido en base a los resultados",
        "btnLabelGoToSurvey": "Hacer ahora",
        "btnLabelHide": "Ocultar",
        "survey": "Cuestionario",
        "btnLabelSubmit": "Enviar",
        "update": "Actualizar",
        "answerAll": "Por favor, contesta a todas las preguntas para poder enviar el cuestionario",
        "answerQuestion": "Por favor, contesta a esta pregunta",
        "btnLabelViewFeedback": "Ver resultados",
        "btnLabelRetakeSurvey": "Repetir Cuestionario",
        "leaveSurveyWarning": "Estás a punto de abandonar el cuestionario",
        "leaveSurveyWarningDesc": "No te preocupes, siempre puedes reiniciar el cuestionario desde tu Perfil.",
        "btnLabelLeave": "Salir",
        "btnLabelStay": "Seguir",
        "preHeaderSurveyFeedback": "Resultados del cuestionario",
        "headerThankYouMessage": "¡Gracias por completar el cuestionario!",
        "headerSurveyFeedback": "Tus resultados de",
        "btnLabelExplore": "Ver contenido recomendado",
        "subHeaderFeedback": "Feedback",
        "headerRecommendedForYou": "Recomendado para ti",
        "headerRecommendedForYouBy": "Recomendado para ti por",
        "helpUsBtn": "Ayúdanos a mejorar",
        "helpUsText": "Ayúdanos a mejorar tu experiencia educativa respondiendo unas preguntas sobre este curso.",
        "thankYouModal": "Gracias por tu valoración!",
        "oneMoreThing": "Una última cosa",
        "notNowBtn": "Ahora no"
    },
    "textAreaPlaceholder": "Escribe algo aquí...",
    "commentBoxLabel": "Espacio para escribir tu recomendación",
    "textAreaAriaLabel": "Espacio para escribir tu respuesta",
    "rating": {
        "oneStar": "una estrella",
        "twoStar": "dos estrellas",
        "threeStar": "tres estrellas",
        "fourStar": "cuatro estrellas",
        "fiveStar": "cinco estrellas",
        "empty": "todavía no hay puntuación"
    },
    "customSurvey": {
        "answersReceived": "Hemos recibido tus respuestas",
        "thanks": "Gracias por tu contribución!"
    },
    "imageAlt": {
        "documentWithStar": "Icono de un documento con una imagen",
        "happyHeartPerson": "Persona feliz con corazones"
    },
    "successPage": {
        "addCert": "Añadir certificado",
        "completedPrograms": "Tus programas completados",
        "completedCourses": "Tus cursos completados"
    },
    "accessibility": {
        "comingSoonSubHeader": "Estamos trabajando en esta página. ¡Gracias por tu paciencia!",
        "comingSoonHeader": "Próximamente..."
    }
}
