{
    "home": "صفحه اصلی",
    "explore": "کاوش کنید",
    "success": "موفقیت",
    "community": "انجمن",
    "news": "اخبار",
    "new": "جدید",
    "earlier": "زودتر",
    "seeAll": "همه را ببین",
    "more": "بیشتر",
    "noNotifications": "در حال حاضر هیچ اعلانی ندارید",
    "notifications": "اطلاعیه",
    "profile": "مشخصات",
    "preferences": "اولویت ها",
    "offerBoard": "تابلوی پیشنهادات",
    "support": "پشتیبانی",
    "helpCenter": "مرکز کمک",
    "learners": "فراگیران",
    "privacyPolicy": "سیاست حفظ حریم خصوصی",
    "logout": "خروج",
    "joinForFree": "ورود به صورت رایگان",
    "subOrgConsent": "از آنجا که این به اشتراک گذاری داده ها بخش مهمی از تجربه دانشگاه است ، ممکن است بدون آن ادامه ندهید.",
    "restrictedContent": "دسترسی محدود"
  }